placementclient/__init__.py
placementclient/base.py
placementclient/client.py
placementclient/exceptions.py
placementclient/tests/__init__.py
placementclient/tests/unit/__init__.py
placementclient/tests/unit/test_placement.py
placementclient/v1/__init__.py
placementclient/v1/allocation_candidates.py
placementclient/v1/allocations.py
placementclient/v1/client.py
placementclient/v1/resource_providers.py
placementclient-1.0.0.dist-info/LICENSE
placementclient-1.0.0.dist-info/METADATA
placementclient-1.0.0.dist-info/WHEEL
placementclient-1.0.0.dist-info/pbr.json
placementclient-1.0.0.dist-info/top_level.txt
placementclient-1.0.0.dist-info/RECORD
